odoo/addons/hr_recruitment_security/README.rst
odoo/addons/hr_recruitment_security/__init__.py
odoo/addons/hr_recruitment_security/__manifest__.py
odoo/addons/hr_recruitment_security/i18n/hr_recruitment_security.pot
odoo/addons/hr_recruitment_security/i18n/it.po
odoo/addons/hr_recruitment_security/readme/CONTRIBUTORS.rst
odoo/addons/hr_recruitment_security/readme/DESCRIPTION.rst
odoo/addons/hr_recruitment_security/security/security.xml
odoo/addons/hr_recruitment_security/static/description/icon.png
odoo/addons/hr_recruitment_security/static/description/index.html
odoo/addons/hr_recruitment_security/tests/__init__.py
odoo/addons/hr_recruitment_security/tests/test_access_rights.py
odoo12_addon_hr_recruitment_security-12.0.1.0.0.99.dev6.dist-info/METADATA
odoo12_addon_hr_recruitment_security-12.0.1.0.0.99.dev6.dist-info/WHEEL
odoo12_addon_hr_recruitment_security-12.0.1.0.0.99.dev6.dist-info/top_level.txt
odoo12_addon_hr_recruitment_security-12.0.1.0.0.99.dev6.dist-info/RECORD
